pyairobotrest/__init__.py
pyairobotrest/client.py
pyairobotrest/const.py
pyairobotrest/exceptions.py
pyairobotrest/models.py
pyairobotrest/py.typed
pyairobotrest-0.3.0.dist-info/licenses/LICENSE
pyairobotrest-0.3.0.dist-info/METADATA
pyairobotrest-0.3.0.dist-info/WHEEL
pyairobotrest-0.3.0.dist-info/top_level.txt
pyairobotrest-0.3.0.dist-info/RECORD
