Metadata-Version: 2.4
Name: pyairobotrest
Version: 0.3.0
Summary: Python library for Airobot thermostat TE1 local REST API
Author-email: Mario Mett <mario@mett.ee>
License-Expression: MIT
Project-URL: Homepage, https://github.com/mettolen/pyairobotrest
Project-URL: Repository, https://github.com/mettolen/pyairobotrest
Project-URL: Issues, https://github.com/mettolen/pyairobotrest/issues
Keywords: airobot,thermostat,rest-api,home-automation
Classifier: Development Status :: 4 - Beta
Classifier: Intended Audience :: Developers
Classifier: Operating System :: OS Independent
Classifier: Programming Language :: Python :: 3
Classifier: Programming Language :: Python :: 3.11
Classifier: Programming Language :: Python :: 3.12
Classifier: Programming Language :: Python :: 3.13
Classifier: Topic :: Home Automation
Requires-Python: >=3.11
License-File: LICENSE
Requires-Dist: aiohttp>=3.9.0
Provides-Extra: dev
Requires-Dist: pytest>=7.0; extra == "dev"
Requires-Dist: pytest-asyncio>=0.21.0; extra == "dev"
Requires-Dist: pytest-cov>=4.0; extra == "dev"
Requires-Dist: pytest-timeout>=2.1.0; extra == "dev"
Requires-Dist: ruff>=0.1.0; extra == "dev"
Requires-Dist: mypy>=1.0; extra == "dev"
Requires-Dist: build>=1.0.0; extra == "dev"
Requires-Dist: twine>=4.0.0; extra == "dev"
Dynamic: license-file
